CompoTree/__init__.py
CompoTree/char_lexicon.py
CompoTree/compo_tree.py
CompoTree/compositions.py
CompoTree/found_results.py
CompoTree/load_data.py
CompoTree/ortho_node.py
CompoTree/radicals.py
CompoTree/struct_cursor.py
CompoTree/ts_variants.py
CompoTree/data/CJKRadicals.txt
CompoTree/data/Unihan_IRGSOurces_kRSUnicode.txt
CompoTree/data/Unihan_Variants.txt
CompoTree/data/asbc5_characters.pkl
CompoTree/data/ids.txt
CompoTree-0.0.1.dist-info/METADATA
CompoTree-0.0.1.dist-info/WHEEL
CompoTree-0.0.1.dist-info/top_level.txt
CompoTree-0.0.1.dist-info/RECORD
